sol_mul/__init__.py
sol_mul/mul.py
sol_mul-0.1.0.dist-info/METADATA
sol_mul-0.1.0.dist-info/WHEEL
sol_mul-0.1.0.dist-info/top_level.txt
sol_mul-0.1.0.dist-info/RECORD
