Metadata-Version: 2.1
Name: sol_mul
Version: 0.1.0
Summary: Default template for PDM package
Author-email: j25ng <jsan2861@gmail.com>
License: MIT
Requires-Python: ==3.11.*
